pyterrier_generative/__init__.py
pyterrier_generative/_algorithms.py
pyterrier_generative/prompts.py
pyterrier_generative/truncation.py
pyterrier_generative/algorithms/__init__.py
pyterrier_generative/algorithms/common.py
pyterrier_generative/algorithms/setwise.py
pyterrier_generative/algorithms/single_window.py
pyterrier_generative/algorithms/sliding_window.py
pyterrier_generative/algorithms/tdpart.py
pyterrier_generative/modelling/__init__.py
pyterrier_generative/modelling/base.py
pyterrier_generative/modelling/lit5.py
pyterrier_generative/modelling/util.py
pyterrier_generative/modelling/variants.py
pyterrier_generative/pt_docs/index.rst
pyterrier_generative-0.1.3.dist-info/licenses/LICENSE
pyterrier_generative-0.1.3.dist-info/METADATA
pyterrier_generative-0.1.3.dist-info/WHEEL
pyterrier_generative-0.1.3.dist-info/top_level.txt
pyterrier_generative-0.1.3.dist-info/RECORD
