Metadata-Version: 2.4
Name: pyterrier-generative
Version: 0.1.3
Summary: PyTerrier Integration for Generative Rankers
Author-email: Andrew Parry <a.parry.1@research.gla.ac.uk>
Project-URL: Repository, https://github.com/Parry-Parry/pyterrier-generative
Project-URL: Bug Tracker, https://github.com/Parry-Parry/pyterrier-generative/issues
Classifier: Programming Language :: Python
Classifier: Operating System :: OS Independent
Classifier: Topic :: Text Processing
Classifier: Topic :: Text Processing :: Indexing
Requires-Python: >=3.10
License-File: LICENSE
Requires-Dist: pyterrier
Requires-Dist: pyterrier_rag
Requires-Dist: transformers[torch]
Requires-Dist: tiktoken
Dynamic: license-file
